ludoman/__init__.py
ludoman/plots.py
ludoman/streams.py
ludoman-1.0.0.dist-info/METADATA
ludoman-1.0.0.dist-info/WHEEL
ludoman-1.0.0.dist-info/top_level.txt
ludoman-1.0.0.dist-info/RECORD
